pyclocklib/__init__.py
pyclocklib-0.0.1.dist-info/METADATA
pyclocklib-0.0.1.dist-info/WHEEL
pyclocklib-0.0.1.dist-info/top_level.txt
pyclocklib-0.0.1.dist-info/RECORD
